LICENSE.txt
MANIFEST.in
README.md
setup.cfg
setup.py
versioneer.py
PkgScript.egg-info/PKG-INFO
PkgScript.egg-info/SOURCES.txt
PkgScript.egg-info/dependency_links.txt
PkgScript.egg-info/requires.txt
PkgScript.egg-info/top_level.txt
pkgscript/__init__.py
pkgscript/_version.py
pkgscript/pkgscript.py
pkgscript/version.py