Metadata-Version: 2.1
Name: PkgScript
Version: 0.6.1
Summary: Python module that allows a packaged module to run properly as a script
Home-page: https://bitbucket.org/padraicshafer/pkgscript
Author: Padraic Shafer
Author-email: pshafer@lbl.gov
License: MIT
Keywords: package script import sibling relative absolute
Platform: UNKNOWN
Classifier: Development Status :: 4 - Beta
Classifier: Intended Audience :: Developers
Classifier: Topic :: Software Development :: Build Tools
Classifier: License :: OSI Approved :: MIT License
Classifier: Programming Language :: Python :: 2
Classifier: Programming Language :: Python :: 2.7
Classifier: Programming Language :: Python :: 3
Classifier: Programming Language :: Python :: 3.6
Classifier: Programming Language :: Python :: 3.7
Classifier: Programming Language :: Python :: 3.8
Classifier: Programming Language :: Python :: 3.9
Classifier: Programming Language :: Python :: 3.10
